{
  "privileges": {
    "type": "dropdown",
    "label": "Who can participate:",
    "value": "everybody",
    "options": {
      "everybody": "Everybody",
      "subs": "Subs",
      "vips": "VIPS",
      "mods": "Mods",
      "broadcaster":"Broadcaster"
    }
  },
  "globalCooldown": {
    "type": "number",
    "label": "Global cooldown (s)",
    "value": 60
  },
  "widgetName": {
    "type": "hidden",
    "value": "Emote Combo Sounds"
  },
  "widgetAuthor": {
    "type": "hidden",
    "value": "lx"
  },
  "widgetVersion": {
    "type": "hidden",
    "value": "1.0"
  },
  "widgetUpdateUrl": {
    "type": "hidden",
    "value": "https://github.com/StreamElements/widgets/blob/master/EmoteComboSounds/"
  }
}
